spotbee/__init__.py
spotbee/__main__.py
spotbee/spotify.py
spotbee/ytsearch.py
spotbee-1.1.0.dist-info/WHEEL
spotbee-1.1.0.dist-info/METADATA
spotbee-1.1.0.dist-info/RECORD
